{"chunk_definitions":[{"chunk_id":"cnx353myzyh3z","chunk_label":"unnamed-chunk-7","document_id":"8B3A4C57","expansion_state":0,"options":{"engine":"r","eval":"F","label":"unnamed-chunk-2"},"row":111,"row_count":1,"visible":true},{"chunk_id":"cjv37djolmw6b","chunk_label":"unnamed-chunk-10","document_id":"8B3A4C57","expansion_state":0,"options":{"engine":"r","eval":"F","label":"unnamed-chunk-6"},"row":140,"row_count":1,"visible":true},{"chunk_id":"cji0ktzba3vux","chunk_label":"unnamed-chunk-11","document_id":"8B3A4C57","expansion_state":0,"options":{"engine":"r","label":"unnamed-chunk-17"},"row":151,"row_count":1,"visible":true},{"chunk_id":"cxkttmwwi69dv","chunk_label":"unnamed-chunk-12","document_id":"8B3A4C57","expansion_state":0,"options":{"engine":"r","label":"unnamed-chunk-26"},"row":158,"row_count":1,"visible":true},{"chunk_id":"c3na9z8qhcm8w","chunk_label":"unnamed-chunk-13","document_id":"8B3A4C57","expansion_state":0,"options":{"engine":"r","label":"unnamed-chunk-30"},"row":165,"row_count":1,"visible":true},{"chunk_id":"c70wcwrh7uhgv","chunk_label":"unnamed-chunk-14","document_id":"8B3A4C57","expansion_state":0,"options":{"engine":"r","label":"unnamed-chunk-53"},"row":172,"row_count":1,"visible":true},{"chunk_id":"c10rl32lnomur","chunk_label":"unnamed-chunk-16","document_id":"8B3A4C57","expansion_state":0,"options":{"engine":"r","eval":"F","label":"unnamed-chunk-80"},"row":220,"row_count":1,"visible":true}],"doc_write_time":1568154885}